inspectshow/__init__.py
inspectshow/__main__.py
inspectshow-1.2.dist-info/DESCRIPTION.rst
inspectshow-1.2.dist-info/METADATA
inspectshow-1.2.dist-info/RECORD
inspectshow-1.2.dist-info/WHEEL
inspectshow-1.2.dist-info/metadata.json
inspectshow-1.2.dist-info/top_level.txt
