Metadata-Version: 2.0
Name: inspectshow
Version: 1.2
Summary: show module internals and corresponding class internals in tree format
Home-page: https://github.com/vadivelmurugank/inspectshow
Author: Vadivel
Author-email: vadivelmurugank@gmail.com
License: MIT
Keywords: inspect show tree
Platform: UNKNOWN
Classifier: Development Status :: 3 - Alpha
Classifier: Intended Audience :: Developers
Classifier: License :: OSI Approved :: Python Software Foundation License
Classifier: Operating System :: OS Independent
Classifier: Programming Language :: Python :: 2.7
Classifier: Programming Language :: Python :: 3.2
Classifier: Programming Language :: Python :: 3.3
Classifier: Programming Language :: Python :: 3.4
Classifier: Programming Language :: Python :: 3.5
Classifier: Programming Language :: Python :: 3.6
Classifier: Topic :: Software Development
